round_using_error/__init__.py
round_using_error/round_using_error.py
round_using_error-1.2.0.dist-info/LICENSE
round_using_error-1.2.0.dist-info/METADATA
round_using_error-1.2.0.dist-info/WHEEL
round_using_error-1.2.0.dist-info/top_level.txt
round_using_error-1.2.0.dist-info/RECORD
