Metadata-Version: 2.1
Name: round_using_error
Version: 1.2.0
Summary: Output numbers +/- error with appropriate rounding.
Home-page: https://github.com/gutow/round_using_error
Author: Jonathan Gutow
Author-email: gutow@uwosh.edu
License: GPL-3.0+
Classifier: Development Status :: 5 - Production/Stable
Classifier: Intended Audience :: Developers
Classifier: Intended Audience :: Education
Classifier: License :: OSI Approved :: GNU General Public License v3 or later (GPLv3+)
Classifier: Programming Language :: Python :: 3
Classifier: Operating System :: OS Independent
License-File: LICENSE
